liftstatus/__init__.py
liftstatus/_version.py
liftstatus/exceptions.py
liftstatus/apis/alterra.py
liftstatus/apis/aspen.py
liftstatus/apis/boyne.py
liftstatus/apis/epic.py
liftstatus/apis/powdr.py
liftstatus/mountains/__init__.py
liftstatus/mountains/britishcolumbia/__init__.py
liftstatus/mountains/britishcolumbia/cypress.py
liftstatus/mountains/britishcolumbia/whistlerblackcomb.py
liftstatus/mountains/california/__init__.py
liftstatus/mountains/california/bearmountain.py
liftstatus/mountains/california/boreal.py
liftstatus/mountains/california/heavenly.py
liftstatus/mountains/california/junemountain.py
liftstatus/mountains/california/kirkwood.py
liftstatus/mountains/california/mammoth.py
liftstatus/mountains/california/northstar.py
liftstatus/mountains/california/palisadestahoe.py
liftstatus/mountains/california/snowsummit.py
liftstatus/mountains/california/snowvalley.py
liftstatus/mountains/california/sodasprings.py
liftstatus/mountains/colorado/__init__.py
liftstatus/mountains/colorado/arapahoebasin.py
liftstatus/mountains/colorado/aspen.py
liftstatus/mountains/colorado/aspenhighlands.py
liftstatus/mountains/colorado/beavercreek.py
liftstatus/mountains/colorado/breckenridge.py
liftstatus/mountains/colorado/buttermilk.py
liftstatus/mountains/colorado/copper.py
liftstatus/mountains/colorado/crestedbutte.py
liftstatus/mountains/colorado/eldora.py
liftstatus/mountains/colorado/keystone.py
liftstatus/mountains/colorado/loveland.py
liftstatus/mountains/colorado/snowmass.py
liftstatus/mountains/colorado/steamboat.py
liftstatus/mountains/colorado/vail.py
liftstatus/mountains/colorado/winterpark.py
liftstatus/mountains/idaho/__init__.py
liftstatus/mountains/idaho/schweitzer.py
liftstatus/mountains/indiana/__init__.py
liftstatus/mountains/indiana/paolipeaks.py
liftstatus/mountains/maine/__init__.py
liftstatus/mountains/maine/pleasant.py
liftstatus/mountains/maine/sugarloaf.py
liftstatus/mountains/maine/sundayriver.py
liftstatus/mountains/michigan/__init__.py
ski_resort_lift_status-1.0.0.dist-info/METADATA
ski_resort_lift_status-1.0.0.dist-info/WHEEL
ski_resort_lift_status-1.0.0.dist-info/licenses/LICENSE
ski_resort_lift_status-1.0.0.dist-info/RECORD
