Metadata-Version: 2.4
Name: ski-resort-lift-status
Version: 1.0.0
Summary: Aggregated reporting of lift status at various ski resorts
Project-URL: Homepage, https://github.com/NietoSkunk/ski-resort-lift-status
Project-URL: Issues, https://github.com/NietoSkunk/ski-resort-lift-status/issues
Project-URL: Changelog, https://github.com/NietoSkunk/ski-resort-lift-status/blob/main/CHANGELOG.md
Author: NietoSkunk
License-File: LICENSE
Classifier: License :: OSI Approved :: MIT License
Classifier: Operating System :: OS Independent
Classifier: Programming Language :: Python :: 3
Requires-Python: >=3.0
Requires-Dist: beautifulsoup4
Requires-Dist: python-dateutil
Requires-Dist: pytz
Requires-Dist: requests
